spintest/__init__.py
spintest/manager.py
spintest/task.py
spintest/types.py
spintest/validator.py
spintest-0.4.2.dist-info/AUTHORS
spintest-0.4.2.dist-info/LICENSE
spintest-0.4.2.dist-info/METADATA
spintest-0.4.2.dist-info/WHEEL
spintest-0.4.2.dist-info/top_level.txt
spintest-0.4.2.dist-info/RECORD
