Metadata-Version: 2.1
Name: spintest
Version: 0.4.2
Summary: Functional scenario interpreter
Home-page: https://github.com/societe-generale/spintest
Author: Matthieu Gouel
Author-email: matthieu.gouel@gmail.com
License: BSD-3-Clause
Platform: UNKNOWN
Classifier: Topic :: Utilities
Classifier: Intended Audience :: Developers
Classifier: Programming Language :: Python
Classifier: Programming Language :: Python :: 3
Classifier: Programming Language :: Python :: 3.6
Classifier: Operating System :: OS Independent
Classifier: License :: OSI Approved :: BSD License
Requires-Dist: colorlog
Requires-Dist: jinja2
Requires-Dist: schema
Requires-Dist: requests
